L3rotect/AntiAnalysis.py
L3rotect/__init__.py
L33rotect-0.2.dist-info/METADATA
L33rotect-0.2.dist-info/WHEEL
L33rotect-0.2.dist-info/top_level.txt
L33rotect-0.2.dist-info/RECORD
