Metadata-Version: 2.1
Name: L33rotect
Version: 0.2
Requires-Dist: psutil
Requires-Dist: uuid
Requires-Dist: wmi
Requires-Dist: requests
Requires-Dist: urllib3
